ollama_data_tools/__init__.py
ollama_data_tools/conversion_tools.py
ollama_data_tools/json_cache.py
ollama_data_tools/ollama_data.py
ollama_data_tools/ollama_data_adapter.py
ollama_data_tools/ollama_data_export.py
ollama_data_tools/ollama_data_query.py
ollama_data_tools/ollama_data_utils.py
ollama_data_tools/regex_path_matcher.py
ollama_data_tools-0.1.1.dist-info/LICENSE
ollama_data_tools-0.1.1.dist-info/METADATA
ollama_data_tools-0.1.1.dist-info/WHEEL
ollama_data_tools-0.1.1.dist-info/entry_points.txt
ollama_data_tools-0.1.1.dist-info/top_level.txt
ollama_data_tools-0.1.1.dist-info/RECORD
