Metadata-Version: 2.1
Name: ollama-data-tools
Version: 0.1.1
Summary: Tools for working with Ollama model data
Home-page: https://github.com/queelius/ollama_data_tools
Author: Alex Towell
Author-email: lex@metafunctor.com
Classifier: Programming Language :: Python :: 3
Classifier: License :: OSI Approved :: MIT License
Classifier: Operating System :: OS Independent
Requires-Python: >=3.6
License-File: LICENSE
